dino_lock_patterns/__init__.py
dino_lock_patterns/postgres_row_lock.py
dino_rabbitmq_consumer/README.md
dino_rabbitmq_consumer/__init__.py
dino_rabbitmq_consumer/config.py
dino_rabbitmq_consumer/rabbitmq_consumer.py
dino_rabbitmq_consumer/rabbitmq_publisher.py
dino_temporal_lib_helper-0.2.0.dist-info/METADATA
dino_temporal_lib_helper-0.2.0.dist-info/WHEEL
dino_temporal_lib_helper-0.2.0.dist-info/RECORD
