Metadata-Version: 2.4
Name: dino-temporal-lib-helper
Version: 0.2.0
Summary: Utilities for RabbitMQ consumer/publisher and Postgres lock patterns.
Project-URL: Homepage, https://example.com/
Project-URL: Repository, https://example.com/repo
Author: Dino Team
License: Proprietary
Keywords: aio-pika,consumer,locks,postgres,publisher,rabbitmq
Classifier: License :: Other/Proprietary License
Classifier: Operating System :: OS Independent
Classifier: Programming Language :: Python :: 3
Classifier: Programming Language :: Python :: 3 :: Only
Classifier: Programming Language :: Python :: 3.10
Classifier: Programming Language :: Python :: 3.11
Requires-Python: >=3.10
Requires-Dist: aio-pika==9.3.1
Requires-Dist: psycopg2-binary
Provides-Extra: test
Requires-Dist: pydevd-pycharm; extra == 'test'
Requires-Dist: pytest-asyncio; extra == 'test'
